humanized_opening_hours/__init__.py
humanized_opening_hours/exceptions.py
humanized_opening_hours/field.ebnf
humanized_opening_hours/field_parser.py
humanized_opening_hours/main.py
humanized_opening_hours/temporal_objects.py
humanized_opening_hours/tests.py
humanized_opening_hours/utils.py
humanized_opening_hours/validators.py
humanized_opening_hours/locales/fr_FR/LC_MESSAGES/HOH.mo
humanized_opening_hours/locales/fr_FR/LC_MESSAGES/HOH.po
osm_humanized_opening_hours-0.6.2.dist-info/DESCRIPTION.rst
osm_humanized_opening_hours-0.6.2.dist-info/METADATA
osm_humanized_opening_hours-0.6.2.dist-info/RECORD
osm_humanized_opening_hours-0.6.2.dist-info/WHEEL
osm_humanized_opening_hours-0.6.2.dist-info/metadata.json
osm_humanized_opening_hours-0.6.2.dist-info/top_level.txt
