Metadata-Version: 2.0
Name: osm-humanized-opening-hours
Version: 0.6.2
Summary: A parser for the opening_hours fields from OpenStreetMap.
Home-page: http://github.com/rezemika/humanized_opening_hours
Author: rezemika
Author-email: reze.mika@gmail.com
License: UNKNOWN
Platform: UNKNOWN
Classifier: Programming Language :: Python
Classifier: Development Status :: 3 - Alpha
Classifier: License :: OSI Approved :: GNU Affero General Public License v3
Classifier: Natural Language :: French
Classifier: Operating System :: OS Independent
Classifier: Programming Language :: Python :: 3
Classifier: Topic :: Utilities
Classifier: Topic :: Other/Nonlisted Topic
Requires-Dist: pytz
Requires-Dist: lark-parser
Requires-Dist: babel
